lxrbckl/__init__.py
lxrbckl/local.py
lxrbckl/openai.py
lxrbckl/remote.py
lxrbckl/screen.py
lxrbckl-3.6.0.dist-info/LICENSE.txt
lxrbckl-3.6.0.dist-info/METADATA
lxrbckl-3.6.0.dist-info/WHEEL
lxrbckl-3.6.0.dist-info/RECORD
