Metadata-Version: 2.1
Name: lxrbckl
Version: 3.6.0
Summary: CRUD tools for local and remote files, enhancing readability and abstraction in lxRbckl projects.
Home-page: https://github.com/lxRbckl/lxRbckl/tree/python
Author: lxRbckl
Author-email: lxrbckl@gmail.com
Requires-Python: >=3.8,<4.0
Classifier: Programming Language :: Python :: 3
Classifier: Programming Language :: Python :: 3.8
Classifier: Programming Language :: Python :: 3.9
Classifier: Programming Language :: Python :: 3.10
Classifier: Programming Language :: Python :: 3.11
Classifier: Programming Language :: Python :: 3.12
Classifier: Programming Language :: Python :: 3.13
Requires-Dist: openai (>=1.3.5,<2.0.0)
Requires-Dist: pyautogui (>=0.9.54,<0.10.0)
Requires-Dist: pygithub (>=2.1.1,<3.0.0)
Requires-Dist: pytest (>=7.4.2,<8.0.0)
Requires-Dist: requests (>=2.31.0,<3.0.0)
